odoo8_addon_l10n_es_aeat_sii-8.0.2.18.2-py3.8-nspkg.pth
odoo_addons/l10n_es_aeat_sii/README.rst
odoo_addons/l10n_es_aeat_sii/__init__.py
odoo_addons/l10n_es_aeat_sii/__openerp__.py
odoo_addons/l10n_es_aeat_sii/hooks.py
odoo_addons/l10n_es_aeat_sii/data/aeat_sii_map_data.xml
odoo_addons/l10n_es_aeat_sii/data/aeat_sii_mapping_registration_keys_data.xml
odoo_addons/l10n_es_aeat_sii/data/ir_config_parameter.xml
odoo_addons/l10n_es_aeat_sii/i18n/bg.po
odoo_addons/l10n_es_aeat_sii/i18n/ca.po
odoo_addons/l10n_es_aeat_sii/i18n/ca_ES.po
odoo_addons/l10n_es_aeat_sii/i18n/cs.po
odoo_addons/l10n_es_aeat_sii/i18n/en_US.po
odoo_addons/l10n_es_aeat_sii/i18n/es.po
odoo_addons/l10n_es_aeat_sii/i18n/es_CO.po
odoo_addons/l10n_es_aeat_sii/i18n/es_CR.po
odoo_addons/l10n_es_aeat_sii/i18n/eu.po
odoo_addons/l10n_es_aeat_sii/i18n/fr.po
odoo_addons/l10n_es_aeat_sii/i18n/gl.po
odoo_addons/l10n_es_aeat_sii/i18n/hr.po
odoo_addons/l10n_es_aeat_sii/i18n/l10n_es_aeat_sii.pot
odoo_addons/l10n_es_aeat_sii/i18n/nl.po
odoo_addons/l10n_es_aeat_sii/i18n/pl.po
odoo_addons/l10n_es_aeat_sii/i18n/pt.po
odoo_addons/l10n_es_aeat_sii/i18n/pt_BR.po
odoo_addons/l10n_es_aeat_sii/i18n/ru.po
odoo_addons/l10n_es_aeat_sii/i18n/sl.po
odoo_addons/l10n_es_aeat_sii/i18n/sv.po
odoo_addons/l10n_es_aeat_sii/i18n/tr.po
odoo_addons/l10n_es_aeat_sii/i18n/vi.po
odoo_addons/l10n_es_aeat_sii/migrations/8.0.2.14.0/post-migration.py
odoo_addons/l10n_es_aeat_sii/models/__init__.py
odoo_addons/l10n_es_aeat_sii/models/account_fiscal_position.py
odoo_addons/l10n_es_aeat_sii/models/account_invoice.py
odoo_addons/l10n_es_aeat_sii/models/aeat_sii.py
odoo_addons/l10n_es_aeat_sii/models/aeat_sii_map.py
odoo_addons/l10n_es_aeat_sii/models/aeat_sii_mapping_registration_keys.py
odoo_addons/l10n_es_aeat_sii/models/product_product.py
odoo_addons/l10n_es_aeat_sii/models/queue_job.py
odoo_addons/l10n_es_aeat_sii/models/res_company.py
odoo_addons/l10n_es_aeat_sii/models/res_partner.py
odoo_addons/l10n_es_aeat_sii/security/aeat_sii.xml
odoo8_addon_l10n_es_aeat_sii-8.0.2.18.2.dist-info/METADATA
odoo8_addon_l10n_es_aeat_sii-8.0.2.18.2.dist-info/WHEEL
odoo8_addon_l10n_es_aeat_sii-8.0.2.18.2.dist-info/namespace_packages.txt
odoo8_addon_l10n_es_aeat_sii-8.0.2.18.2.dist-info/top_level.txt
odoo8_addon_l10n_es_aeat_sii-8.0.2.18.2.dist-info/RECORD
