Metadata-Version: 2.1
Name: odoo8-addon-l10n-es-aeat-sii
Version: 8.0.2.18.2
Summary: Suministro Inmediato de Información en el IVA
Home-page: https://odoospain.odoo.com
Author: Acysos S.L.,Diagram,Minorisa,Studio73,FactorLibre,Comunitea,Otherway,Tecnativa,Odoo Community Association (OCA)
Author-email: support@odoo-community.org
License: AGPL-3
Platform: UNKNOWN
Classifier: Programming Language :: Python
Classifier: Framework :: Odoo
Classifier: License :: OSI Approved :: GNU Affero General Public License v3
Requires-Python: ~=2.7
Requires-Dist: odoo8-addon-account-invoice-currency
Requires-Dist: odoo8-addon-account-refund-original
Requires-Dist: odoo8-addon-connector
Requires-Dist: odoo8-addon-l10n-es-aeat
Requires-Dist: odoo (<9.0a,>=8.0a)
Requires-Dist: pyOpenSSL (>=0.15)
Requires-Dist: requests
Requires-Dist: zeep
